functag/__init__.py
functag/py.typed
functag/registry.py
functag-1.2.7.dist-info/METADATA
functag-1.2.7.dist-info/WHEEL
functag-1.2.7.dist-info/top_level.txt
functag-1.2.7.dist-info/RECORD
